{
  "indexes": [
    {
      "collectionGroup": "patients",
      "queryScope": "COLLECTION",
      "fields": [
        { "fieldPath": "therapist_email", "order": "ASCENDING" },
        { "fieldPath": "full_name", "order": "ASCENDING" }
      ]
    },
    {
      "collectionGroup": "appointments",
      "queryScope": "COLLECTION",
      "fields": [
        { "fieldPath": "therapist_email", "order": "ASCENDING" },
        { "fieldPath": "date", "order": "ASCENDING" }
      ]
    },
    {
      "collectionGroup": "appointments",
      "queryScope": "COLLECTION",
      "fields": [
        { "fieldPath": "patient_id", "order": "ASCENDING" },
        { "fieldPath": "date", "order": "DESCENDING" }
      ]
    },
    {
      "collectionGroup": "appointments",
      "queryScope": "COLLECTION",
      "fields": [
        { "fieldPath": "series_id", "order": "ASCENDING" },
        { "fieldPath": "status", "order": "ASCENDING" },
        { "fieldPath": "date", "order": "ASCENDING" }
      ]
    },
    {
      "collectionGroup": "treatments",
      "queryScope": "COLLECTION",
      "fields": [
        { "fieldPath": "therapist_email", "order": "ASCENDING" },
        { "fieldPath": "date", "order": "DESCENDING" }
      ]
    },
    {
      "collectionGroup": "treatments",
      "queryScope": "COLLECTION",
      "fields": [
        { "fieldPath": "patient_id", "order": "ASCENDING" },
        { "fieldPath": "treatment_number", "order": "DESCENDING" }
      ]
    },
    {
      "collectionGroup": "progress",
      "queryScope": "COLLECTION",
      "fields": [
        { "fieldPath": "patient_id", "order": "ASCENDING" },
        { "fieldPath": "date", "order": "ASCENDING" }
      ]
    },
    {
      "collectionGroup": "templates",
      "queryScope": "COLLECTION",
      "fields": [
        { "fieldPath": "therapist_email", "order": "ASCENDING" },
        { "fieldPath": "name", "order": "ASCENDING" }
      ]
    },
    {
      "collectionGroup": "intakeForms",
      "queryScope": "COLLECTION",
      "fields": [
        { "fieldPath": "therapist_email", "order": "ASCENDING" },
        { "fieldPath": "date", "order": "DESCENDING" }
      ]
    }
  ],
  "fieldOverrides": []
}
