{
  "packageId": "app.web.speech_therapy_clinic.twa",
  "host": "speech-therapy-clinic.web.app",
  "name": "ניהול קלינקה-קלינאית תקשורת",
  "launcherName": "קלינאית",
  "display": "standalone",
  "themeColor": "#0D9488",
  "themeColorDark": "#000000",
  "navigationColor": "#000000",
  "navigationColorDark": "#000000",
  "navigationDividerColor": "#000000",
  "navigationDividerColorDark": "#000000",
  "backgroundColor": "#FFFFFF",
  "enableNotifications": true,
  "startUrl": "/",
  "iconUrl": "https://speech-therapy-clinic.web.app/icon-512.png",
  "maskableIconUrl": "https://speech-therapy-clinic.web.app/icon-512.png",
  "splashScreenFadeOutDuration": 300,
  "signingKey": {
    "path": "/workspaces/speech-therapy-clinic/android.keystore",
    "alias": "android"
  },
  "appVersionName": "1",
  "appVersionCode": 1,
  "shortcuts": [],
  "generatorApp": "bubblewrap-cli",
  "webManifestUrl": "https://speech-therapy-clinic.web.app/manifest.json",
  "fallbackType": "customtabs",
  "features": {},
  "alphaDependencies": {
    "enabled": false
  },
  "enableSiteSettingsShortcut": true,
  "isChromeOSOnly": false,
  "isMetaQuest": false,
  "fullScopeUrl": "https://speech-therapy-clinic.web.app/",
  "minSdkVersion": 21,
  "orientation": "portrait",
  "fingerprints": [],
  "additionalTrustedOrigins": [],
  "retainedBundles": [],
  "protocolHandlers": [],
  "fileHandlers": [],
  "launchHandlerClientMode": "",
  "displayOverride": [],
  "appVersion": "1"
}